cc_backend_lib/__init__.py
cc_backend_lib/async_either.py
cc_backend_lib/cache/__init__.py
cc_backend_lib/cache/base_cache.py
cc_backend_lib/cache/cache.py
cc_backend_lib/cache/cache_serializer.py
cc_backend_lib/cache/dict_cache.py
cc_backend_lib/cache/identity_serializer.py
cc_backend_lib/cache/pydantic_serializer.py
cc_backend_lib/cache/redis_cache.py
cc_backend_lib/cache/signature.py
cc_backend_lib/clients/__init__.py
cc_backend_lib/clients/api_client.py
cc_backend_lib/clients/countries_client.py
cc_backend_lib/clients/model_api_client.py
cc_backend_lib/clients/predictions_client.py
cc_backend_lib/clients/scheduler_client.py
cc_backend_lib/clients/users_client.py
cc_backend_lib/dal.py
cc_backend_lib/email/__init__.py
cc_backend_lib/email/emailer.py
cc_backend_lib/email/mailjet_emailer.py
cc_backend_lib/email/mailjet_models.py
cc_backend_lib/errors/__init__.py
cc_backend_lib/errors/http_error.py
cc_backend_lib/helpers.py
cc_backend_lib/models/__init__.py
cc_backend_lib/models/country.py
cc_backend_lib/models/emailer.py
cc_backend_lib/models/prediction.py
cc_backend_lib/models/scales.py
cc_backend_lib/models/time_partition.py
cc_backend_lib/models/user.py
cc_backend_lib-0.17.0.dist-info/LICENSE
cc_backend_lib-0.17.0.dist-info/WHEEL
cc_backend_lib-0.17.0.dist-info/METADATA
cc_backend_lib-0.17.0.dist-info/RECORD
