Metadata-Version: 2.1
Name: cc-backend-lib
Version: 0.17.0
Summary: A library with classes and types used througout the backend for Conflict Cartographer
Home-page: https://www.github.com/prio-data/cc_backend_lib
License: MIT
Author: peder2911
Author-email: pglandsverk@gmail.com
Requires-Python: >=3.8,<4.0
Classifier: License :: OSI Approved :: MIT License
Classifier: Programming Language :: Python :: 3
Classifier: Programming Language :: Python :: 3.10
Classifier: Programming Language :: Python :: 3.8
Classifier: Programming Language :: Python :: 3.9
Requires-Dist: PyMonad (>=2.4.0,<3.0.0)
Requires-Dist: aiohttp (>=3.8.1,<4.0.0)
Requires-Dist: email-validator (>=1.1.3,<2.0.0)
Requires-Dist: geojson-pydantic (>=0.3.1,<0.4.0)
Requires-Dist: mailjet-rest (>=1.3.4,<2.0.0)
Requires-Dist: pydantic (>=1.9.0,<2.0.0)
Requires-Dist: redis (>=4.1.2,<5.0.0)
Requires-Dist: toolz (>=0.11.2,<0.12.0)
